LexBuilder/BaseCppLexer.py
LexBuilder/BasePyLexer.py
LexBuilder/Builder.py
LexBuilder/__init__.py
LexBuilder-1.3.0.dist-info/LICENSE
LexBuilder-1.3.0.dist-info/METADATA
LexBuilder-1.3.0.dist-info/WHEEL
LexBuilder-1.3.0.dist-info/top_level.txt
LexBuilder-1.3.0.dist-info/RECORD
