Metadata-Version: 2.1
Name: LexBuilder
Version: 1.3.0
Summary: Library for automatic construction of lexers
Author: Alexander554
Author-email: gaa.28112008@gmail.com
Keywords: lexbuilder python c++ lexer
Classifier: Programming Language :: Python :: 3.11
Classifier: License :: OSI Approved :: MIT License
Classifier: Operating System :: OS Independent
Requires-Python: >=3.7
License-File: LICENSE
